setup.py
hacker_news.egg-info/PKG-INFO
hacker_news.egg-info/SOURCES.txt
hacker_news.egg-info/dependency_links.txt
hacker_news.egg-info/requires.txt
hacker_news.egg-info/top_level.txt
hn/__init__.py
hn/hn.py
hn/post.py
hn/user.py